antdb/__init__.py
antdb/py.typed
antdb/sgbd.py
antdb-0.1.0.dist-info/METADATA
antdb-0.1.0.dist-info/WHEEL
antdb-0.1.0.dist-info/RECORD
